<?xml version="1.0" encoding="UTF-8"?>
<ofd:Page xmlns:ofd="http://www.ofdspec.org/2016"><ofd:Area><ofd:PhysicalBox>0 0 210.0157 297.0107</ofd:PhysicalBox></ofd:Area><ofd:Content><ofd:Layer ID="116"><ofd:TextObject ID="117" CTM="0.3528 0 0 0.3528 0 0" Boundary="117.7537 19.5834 22.5647 2.9623" Font="115" Size="9"><ofd:CGTransform CodePosition="0" CodeCount="7" GlyphCount="7"><ofd:Glyphs>2 3 4 5 6 7 8</ofd:Glyphs></ofd:CGTransform><ofd:TextCode X="0" Y="7.488" DeltaX="g 6 9">浏览</ofd:TextCode></ofd:TextObject><ofd:TextObject ID="120" CTM="0.3528 0 0 0.3528 0 0" Boundary="140.783 20.0216 6.0579 2.2479" Font="114" Size="9"><ofd:CGTransform CodePosition="0" CodeCount="3" GlyphCount="3"><ofd:Glyphs>2 3 4</ofd:Glyphs></ofd:CGTransform><ofd:TextCode X="0" Y="6.246" DeltaX="7.677 3.96">Web</ofd:TextCode></ofd:TextObject><ofd:TextObject ID="121" CTM="0.3528 0 0 0.3528 0 0" Boundary="147.3129 19.5834 36.7792 2.9496" Font="115" Size="9"><ofd:CGTransform CodePosition="0" CodeCount="12" GlyphCount="12"><ofd:Glyphs>9 10 11 12 13 14 15 16 10 17 18 19</ofd:Glyphs></ofd:CGTransform><ofd:TextCode X="0" Y="7.488" DeltaX="g 11 9">（册）</ofd:TextCode></ofd:TextObject><ofd:TextObject ID="126" CTM="0.3528 0 0 0.3528 0 0" Boundary="185.4129 22.225 0.4762 0" Font="114" Size="9"><ofd:CGTransform CodePosition="0" CodeCount="1" GlyphCount="1"><ofd:Glyphs>1</ofd:Glyphs></ofd:CGTransform><ofd:TextCode X="0" Y="0"> </ofd:TextCode></ofd:TextObject><ofd:PathObject ID="127" CTM="0.3528 0 0 0.3528 0 0" Boundary="24.9005 23.8337 161.0184 0.254" Stroke="false" Fill="true" Rule="Even-Odd"><ofd:FillColor Value="0 0 0"/><ofd:AbbreviatedData>M 0 0.72 L 456.43 0.72 L 456.43 0 L 0 0 C </ofd:AbbreviatedData></ofd:PathObject><ofd:TextObject ID="128" CTM="0.3528 0 0 0.3528 0 0" Boundary="32.8168 267.716 0.4762 0" Font="114" Size="9"><ofd:CGTransform CodePosition="0" CodeCount="1" GlyphCount="1"><ofd:Glyphs>1</ofd:Glyphs></ofd:CGTransform><ofd:TextCode X="0" Y="0"> </ofd:TextCode></ofd:TextObject><ofd:TextObject ID="129" CTM="0.3528 0 0 0.3528 0 0" Boundary="35.4824 276.1827 0.4762 0" Font="114" Size="9"><ofd:CGTransform CodePosition="0" CodeCount="1" GlyphCount="1"><ofd:Glyphs>1</ofd:Glyphs></ofd:CGTransform><ofd:TextCode X="0" Y="0"> </ofd:TextCode></ofd:TextObject><ofd:TextObject ID="130" CTM="0.3528 0 0 0.3528 0 0" Boundary="105.0114 28.2244 7.8876 3.4518" LineWidth="0.3017" Font="115" Size="10.56" Stroke="true"><ofd:StrokeColor Value="0 0 0"/><ofd:CGTransform CodePosition="0" CodeCount="2" GlyphCount="2"><ofd:Glyphs>20 21</ofd:Glyphs></ofd:CGTransform><ofd:TextCode X="0" Y="8.6939" DeltaX="10.56"></ofd:TextCode></ofd:TextObject><ofd:TextObject ID="131" CTM="0.3528 0 0 0.3528 0 0" Boundary="112.4088 31.2382 0.6652 0.1065" LineWidth="0.3017" Font="115" Size="10.56" Stroke="true"><ofd:StrokeColor Value="0 0 0"/><ofd:CGTransform CodePosition="0" CodeCount="1" GlyphCount="1"><ofd:Glyphs>1</ofd:Glyphs></ofd:CGTransform><ofd:TextCode X="0.1508" Y="0.1509"> </ofd:TextCode></ofd:TextObject><ofd:TextObject ID="132" CTM="0.3528 0 0 0.3528 0 0" Boundary="32.8168 37.169 2.0415 2.5295" Font="115" Size="10.56"><ofd:CGTransform CodePosition="0" CodeCount="1" GlyphCount="1"><ofd:Glyphs>22</ofd:Glyphs></ofd:CGTransform><ofd:TextCode X="0" Y="7.3392">1</ofd:TextCode></ofd:TextObject><ofd:TextObject ID="134" CTM="0.3528 0 0 0.3528 0 0" Boundary="34.6795 39.7581 0.5588 0" Font="133" Size="10.56"><ofd:CGTransform CodePosition="0" CodeCount="1" GlyphCount="1"><ofd:Glyphs>3</ofd:Glyphs></ofd:CGTransform><ofd:TextCode X="0" Y="0"> </ofd:TextCode></ofd:TextObject><ofd:TextObject ID="135" CTM="0.3528 0 0 0.3528 0 0" Boundary="40.2237 36.6586 15.259 3.4608" Font="115" Size="10.56"><ofd:CGTransform CodePosition="0" CodeCount="4" GlyphCount="4"><ofd:Glyphs>11 12 23 24</ofd:Glyphs></ofd:CGTransform><ofd:TextCode X="0" Y="8.7859" DeltaX="g 2 10.56 10.4438"></ofd:TextCode></ofd:TextObject><ofd:TextObject ID="136" CTM="0.3528 0 0 0.3528 0 0" Boundary="55.0404 37.2397 129.5455 2.5667" Font="114" Size="10.56"><ofd:CGTransform CodePosition="0" CodeCount="139" GlyphCount="139"><ofd:Glyphs>1 5 5 5 5 5 5 5 5 5 5 5 5 5 5 5 5 5 5 5 5 5 5 5 5 5 5 5 5 5 5 5 5 5 5 5 5 5 5 5 5 5 5 5 5 5 5 5 5 5 5 5 5 5 5 5 5 5 5 5 5 5 5 5 5 5 5 5 5 5 5 5 5 5 5 5 5 5 5 5 5 5 5 5 5 5 5 5 5 5 5 5 5 5 5 5 5 5 5 5 5 5 5 5 5 5 5 5 5 5 5 5 5 5 5 5 5 5 5 5 5 5 5 5 5 5 5 5 5 5 5 5 5 5 5 5 5 1 6</ofd:Glyphs></ofd:CGTransform><ofd:TextCode X="0" Y="7.1386" DeltaX="2.4 g 31 2.64 2.67 g 31 2.64 2.66 g 31 2.64 2.6401 g 31 2.64 2.67 g 8 2.64 0.12"> ........................................................................................................................................ 1</ofd:TextCode></ofd:TextObject><ofd:TextObject ID="144" CTM="0.3528 0 0 0.3528 0 0" Boundary="184.4816 39.7581 0.5588 0" Font="133" Size="10.56"><ofd:CGTransform CodePosition="0" CodeCount="1" GlyphCount="1"><ofd:Glyphs>3</ofd:Glyphs></ofd:CGTransform><ofd:TextCode X="0" Y="0"> </ofd:TextCode></ofd:TextObject><ofd:TextObject ID="145" CTM="0.3528 0 0 0.3528 0 0" Boundary="40.2237 45.6356 5.7668 2.5742" Font="115" Size="10.56"><ofd:CGTransform CodePosition="0" CodeCount="3" GlyphCount="3"><ofd:Glyphs>22 25 22</ofd:Glyphs></ofd:CGTransform><ofd:TextCode X="0" Y="7.3392" DeltaX="g 2 5.28">1.1</ofd:TextCode></ofd:TextObject><ofd:TextObject ID="146" CTM="0.3528 0 0 0.3528 0 0" Boundary="45.7694 48.2247 0.5588 0" Font="133" Size="10.56"><ofd:CGTransform CodePosition="0" CodeCount="1" GlyphCount="1"><ofd:Glyphs>3</ofd:Glyphs></ofd:CGTransform><ofd:TextCode X="0" Y="0"> </ofd:TextCode></ofd:TextObject><ofd:TextObject ID="147" CTM="0.3528 0 0 0.3528 0 0" Boundary="55.0404 45.1103 7.7897 3.4757" Font="115" Size="10.56"><ofd:CGTransform CodePosition="0" CodeCount="2" GlyphCount="2"><ofd:Glyphs>26 27</ofd:Glyphs></ofd:CGTransform><ofd:TextCode X="0" Y="8.8282" DeltaX="10.56"></ofd:TextCode></ofd:TextObject><ofd:TextObject ID="148" CTM="0.3528 0 0 0.3528 0 0" Boundary="62.4487 45.7064 122.1372 2.5667" Font="114" Size="10.56"><ofd:CGTransform CodePosition="0" CodeCount="131" GlyphCount="131"><ofd:Glyphs>1 5 5 5 5 5 5 5 5 5 5 5 5 5 5 5 5 5 5 5 5 5 5 5 5 5 5 5 5 5 5 5 5 5 5 5 5 5 5 5 5 5 5 5 5 5 5 5 5 5 5 5 5 5 5 5 5 5 5 5 5 5 5 5 5 5 5 5 5 5 5 5 5 5 5 5 5 5 5 5 5 5 5 5 5 5 5 5 5 5 5 5 5 5 5 5 5 5 5 5 5 5 5 5 5 5 5 5 5 5 5 5 5 5 5 5 5 5 5 5 5 5 5 5 5 5 5 5 5 1 6</ofd:Glyphs></ofd:CGTransform><ofd:TextCode X="0" Y="7.1386" DeltaX="2.55 g 63 2.64 2.66 g 31 2.64 2.67 g 32 2.64 0.1201"> ................................................................................................................................ 1</ofd:TextCode></ofd:TextObject><ofd:TextObject ID="155" CTM="0.3528 0 0 0.3528 0 0" Boundary="184.4816 48.2247 0.5588 0" Font="133" Size="10.56"><ofd:CGTransform CodePosition="0" CodeCount="1" GlyphCount="1"><ofd:Glyphs>3</ofd:Glyphs></ofd:CGTransform><ofd:TextCode X="0" Y="0"> </ofd:TextCode></ofd:TextObject><ofd:TextObject ID="156" CTM="0.3528 0 0 0.3528 0 0" Boundary="40.2237 54.1023 5.9158 2.5742" Font="115" Size="10.56"><ofd:CGTransform CodePosition="0" CodeCount="3" GlyphCount="3"><ofd:Glyphs>22 25 28</ofd:Glyphs></ofd:CGTransform><ofd:TextCode X="0" Y="7.3392" DeltaX="g 2 5.28">1.2</ofd:TextCode></ofd:TextObject><ofd:TextObject ID="157" CTM="0.3528 0 0 0.3528 0 0" Boundary="45.7694 56.6914 0.5588 0" Font="133" Size="10.56"><ofd:CGTransform CodePosition="0" CodeCount="1" GlyphCount="1"><ofd:Glyphs>3</ofd:Glyphs></ofd:CGTransform><ofd:TextCode X="0" Y="0"> </ofd:TextCode></ofd:TextObject><ofd:TextObject ID="158" CTM="0.3528 0 0 0.3528 0 0" Boundary="55.0404 53.577 15.2739 3.4907" Font="115" Size="10.56"><ofd:CGTransform CodePosition="0" CodeCount="4" GlyphCount="4"><ofd:Glyphs>29 30 31 32</ofd:Glyphs></ofd:CGTransform><ofd:TextCode X="0" Y="8.8282" DeltaX="g 2 10.56 10.4438">档概</ofd:TextCode></ofd:TextObject><ofd:TextObject ID="159" CTM="0.3528 0 0 0.3528 0 0" Boundary="69.8676 54.1731 114.7183 2.5667" Font="114" Size="10.56"><ofd:CGTransform CodePosition="0" CodeCount="123" GlyphCount="123"><ofd:Glyphs>5 5 5 5 5 5 5 5 5 5 5 5 5 5 5 5 5 5 5 5 5 5 5 5 5 5 5 5 5 5 5 5 5 5 5 5 5 5 5 5 5 5 5 5 5 5 5 5 5 5 5 5 5 5 5 5 5 5 5 5 5 5 5 5 5 5 5 5 5 5 5 5 5 5 5 5 5 5 5 5 5 5 5 5 5 5 5 5 5 5 5 5 5 5 5 5 5 5 5 5 5 5 5 5 5 5 5 5 5 5 5 5 5 5 5 5 5 5 5 5 5 1 6</ofd:Glyphs></ofd:CGTransform><ofd:TextCode X="0" Y="7.1386" DeltaX="g 63 2.64 2.66 g 31 2.64 2.67 g 25 2.64 0.1201">......................................................................................................................... 1</ofd:TextCode></ofd:TextObject><ofd:TextObject ID="165" CTM="0.3528 0 0 0.3528 0 0" Boundary="184.4816 56.6914 0.5588 0" Font="133" Size="10.56"><ofd:CGTransform CodePosition="0" CodeCount="1" GlyphCount="1"><ofd:Glyphs>3</ofd:Glyphs></ofd:CGTransform><ofd:TextCode X="0" Y="0"> </ofd:TextCode></ofd:TextObject><ofd:TextObject ID="166" CTM="0.3528 0 0 0.3528 0 0" Boundary="32.8168 62.5839 2.1905 2.5146" Font="115" Size="10.56"><ofd:CGTransform CodePosition="0" CodeCount="1" GlyphCount="1"><ofd:Glyphs>28</ofd:Glyphs></ofd:CGTransform><ofd:TextCode X="0" Y="7.2969">2</ofd:TextCode></ofd:TextObject><ofd:TextObject ID="167" CTM="0.3528 0 0 0.3528 0 0" Boundary="34.6795 65.1581 0.5588 0" Font="133" Size="10.56"><ofd:CGTransform CodePosition="0" CodeCount="1" GlyphCount="1"><ofd:Glyphs>3</ofd:Glyphs></ofd:CGTransform><ofd:TextCode X="0" Y="0"> </ofd:TextCode></ofd:TextObject><ofd:TextObject ID="168" CTM="0.3528 0 0 0.3528 0 0" Boundary="40.2237 62.4944 6.1468 2.6636" Font="115" Size="10.56"><ofd:CGTransform CodePosition="0" CodeCount="4" GlyphCount="4"><ofd:Glyphs>33 34 35 1</ofd:Glyphs></ofd:CGTransform><ofd:TextCode X="0" Y="7.5504" DeltaX="g 3 5.28">Web </ofd:TextCode></ofd:TextObject><ofd:TextObject ID="169" CTM="0.3528 0 0 0.3528 0 0" Boundary="47.6744 62.0437 33.7478 3.4757" Font="115" Size="10.56"><ofd:CGTransform CodePosition="0" CodeCount="9" GlyphCount="9"><ofd:Glyphs>9 36 11 12 37 38 39 26 40</ofd:Glyphs></ofd:CGTransform><ofd:TextCode X="0" Y="8.8282" DeltaX="10.4438 10.56 10.4438 10.56 10.4438 10.56 10.4438 10.56"></ofd:TextCode></ofd:TextObject><ofd:TextObject ID="170" CTM="0.3528 0 0 0.3528 0 0" Boundary="81.0013 62.6397 103.5846 2.5667" Font="114" Size="10.56"><ofd:CGTransform CodePosition="0" CodeCount="112" GlyphCount="112"><ofd:Glyphs>1 5 5 5 5 5 5 5 5 5 5 5 5 5 5 5 5 5 5 5 5 5 5 5 5 5 5 5 5 5 5 5 5 5 5 5 5 5 5 5 5 5 5 5 5 5 5 5 5 5 5 5 5 5 5 5 5 5 5 5 5 5 5 5 5 5 5 5 5 5 5 5 5 5 5 5 5 5 5 5 5 5 5 5 5 5 5 5 5 5 5 5 5 5 5 5 5 5 5 5 5 5 5 5 5 5 5 5 5 5 1 6</ofd:Glyphs></ofd:CGTransform><ofd:TextCode X="0" Y="7.1385" DeltaX="0.12 g 31 2.64 2.66 g 63 2.64 2.67 g 12 2.64 2.6399 0.1201"> ............................................................................................................. 1</ofd:TextCode></ofd:TextObject><ofd:TextObject ID="177" CTM="0.3528 0 0 0.3528 0 0" Boundary="184.4816 65.1581 0.5588 0" Font="133" Size="10.56"><ofd:CGTransform CodePosition="0" CodeCount="1" GlyphCount="1"><ofd:Glyphs>3</ofd:Glyphs></ofd:CGTransform><ofd:TextCode X="0" Y="0"> </ofd:TextCode></ofd:TextObject><ofd:TextObject ID="178" CTM="0.3528 0 0 0.3528 0 0" Boundary="40.2237 71.0356 5.7668 2.5742" Font="115" Size="10.56"><ofd:CGTransform CodePosition="0" CodeCount="3" GlyphCount="3"><ofd:Glyphs>28 25 22</ofd:Glyphs></ofd:CGTransform><ofd:TextCode X="0" Y="7.3392" DeltaX="g 2 5.28">2.1</ofd:TextCode></ofd:TextObject><ofd:TextObject ID="179" CTM="0.3528 0 0 0.3528 0 0" Boundary="45.7694 73.6247 0.5588 0" Font="133" Size="10.56"><ofd:CGTransform CodePosition="0" CodeCount="1" GlyphCount="1"><ofd:Glyphs>3</ofd:Glyphs></ofd:CGTransform><ofd:TextCode X="0" Y="0"> </ofd:TextCode></ofd:TextObject><ofd:TextObject ID="180" CTM="0.3528 0 0 0.3528 0 0" Boundary="55.0404 70.5103 48.6082 3.5018" Font="115" Size="10.56"><ofd:CGTransform CodePosition="0" CodeCount="13" GlyphCount="13"><ofd:Glyphs>41 6 7 42 43 44 45 46 47 48 49 26 40</ofd:Glyphs></ofd:CGTransform><ofd:TextCode X="0" Y="8.8282" DeltaX="g 2 10.56 10.4438 10.56 10.4438 10.56 10.4438 10.56 10.4438 10.56 10.4438 10.56">浏览遵循</ofd:TextCode></ofd:TextObject><ofd:TextObject ID="181" CTM="0.3528 0 0 0.3528 0 0" Boundary="103.2263 71.1064 81.3596 2.5667" Font="114" Size="10.56"><ofd:CGTransform CodePosition="0" CodeCount="88" GlyphCount="88"><ofd:Glyphs>1 5 5 5 5 5 5 5 5 5 5 5 5 5 5 5 5 5 5 5 5 5 5 5 5 5 5 5 5 5 5 5 5 5 5 5 5 5 5 5 5 5 5 5 5 5 5 5 5 5 5 5 5 5 5 5 5 5 5 5 5 5 5 5 5 5 5 5 5 5 5 5 5 5 5 5 5 5 5 5 5 5 5 5 5 5 1 6</ofd:Glyphs></ofd:CGTransform><ofd:TextCode X="0" Y="7.1385" DeltaX="0.48 g 31 2.64 2.66 g 31 2.64 2.67 g 21 2.64 0.1201"> ..................................................................................... 1</ofd:TextCode></ofd:TextObject><ofd:TextObject ID="187" CTM="0.3528 0 0 0.3528 0 0" Boundary="184.4816 73.6247 0.5588 0" Font="133" Size="10.56"><ofd:CGTransform CodePosition="0" CodeCount="1" GlyphCount="1"><ofd:Glyphs>3</ofd:Glyphs></ofd:CGTransform><ofd:TextCode X="0" Y="0"> </ofd:TextCode></ofd:TextObject><ofd:TextObject ID="188" CTM="0.3528 0 0 0.3528 0 0" Boundary="40.2237 79.5172 5.9158 2.5593" Font="115" Size="10.56"><ofd:CGTransform CodePosition="0" CodeCount="3" GlyphCount="3"><ofd:Glyphs>28 25 28</ofd:Glyphs></ofd:CGTransform><ofd:TextCode X="0" Y="7.2969" DeltaX="g 2 5.28">2.2</ofd:TextCode></ofd:TextObject><ofd:TextObject ID="189" CTM="0.3528 0 0 0.3528 0 0" Boundary="45.7694 82.0914 0.5588 0" Font="133" Size="10.56"><ofd:CGTransform CodePosition="0" CodeCount="1" GlyphCount="1"><ofd:Glyphs>3</ofd:Glyphs></ofd:CGTransform><ofd:TextCode X="0" Y="0"> </ofd:TextCode></ofd:TextObject><ofd:TextObject ID="190" CTM="0.3528 0 0 0.3528 0 0" Boundary="55.0404 79.4278 5.9419 2.6338" Font="115" Size="10.56"><ofd:CGTransform CodePosition="0" CodeCount="3" GlyphCount="3"><ofd:Glyphs>33 34 35</ofd:Glyphs></ofd:CGTransform><ofd:TextCode X="0" Y="7.5504" DeltaX="g 2 5.28">Web</ofd:TextCode></ofd:TextObject><ofd:TextObject ID="191" CTM="0.3528 0 0 0.3528 0 0" Boundary="61.5597 78.9919 20.0684 3.4758" Font="115" Size="10.56"><ofd:CGTransform CodePosition="0" CodeCount="6" GlyphCount="6"><ofd:Glyphs>11 12 50 51 52 53</ofd:Glyphs></ofd:CGTransform><ofd:TextCode X="0" Y="8.7859" DeltaX="10.4438 10.56 10.4438 10.56 10.4438">：</ofd:TextCode></ofd:TextObject><ofd:TextObject ID="192" CTM="0.3528 0 0 0.3528 0 0" Boundary="83.753 79.5731 101.131 2.5667" Font="114" Size="10.56"><ofd:CGTransform CodePosition="0" CodeCount="109" GlyphCount="109"><ofd:Glyphs>1 5 5 5 5 5 5 5 5 5 5 5 5 5 5 5 5 5 5 5 5 5 5 5 5 5 5 5 5 5 5 5 5 5 5 5 5 5 5 5 5 5 5 5 5 5 5 5 5 5 5 5 5 5 5 5 5 5 5 5 5 5 5 5 5 5 5 5 5 5 5 5 5 5 5 5 5 5 5 5 5 5 5 5 5 5 5 5 5 5 5 5 5 5 5 5 5 5 5 5 5 5 5 5 5 5 5 1 7</ofd:Glyphs></ofd:CGTransform><ofd:TextCode X="0" Y="7.1385" DeltaX="0.24 g 31 2.64 2.66 g 63 2.64 2.6701 g 10 2.64 0.12"> .......................................................................................................... 2</ofd:TextCode></ofd:TextObject><ofd:TextObject ID="199" CTM="0.3528 0 0 0.3528 0 0" Boundary="184.4816 82.0914 0.5588 0" Font="133" Size="10.56"><ofd:CGTransform CodePosition="0" CodeCount="1" GlyphCount="1"><ofd:Glyphs>3</ofd:Glyphs></ofd:CGTransform><ofd:TextCode X="0" Y="0"> </ofd:TextCode></ofd:TextObject><ofd:TextObject ID="200" CTM="0.3528 0 0 0.3528 0 0" Boundary="40.2237 87.9945 5.9158 2.5593" Font="115" Size="10.56"><ofd:CGTransform CodePosition="0" CodeCount="3" GlyphCount="3"><ofd:Glyphs>28 25 54</ofd:Glyphs></ofd:CGTransform><ofd:TextCode X="0" Y="7.2969" DeltaX="g 2 5.28">2.3</ofd:TextCode></ofd:TextObject><ofd:TextObject ID="201" CTM="0.3528 0 0 0.3528 0 0" Boundary="45.7694 90.5687 0.5588 0" Font="133" Size="10.56"><ofd:CGTransform CodePosition="0" CodeCount="1" GlyphCount="1"><ofd:Glyphs>3</ofd:Glyphs></ofd:CGTransform><ofd:TextCode X="0" Y="0"> </ofd:TextCode></ofd:TextObject><ofd:TextObject ID="202" CTM="0.3528 0 0 0.3528 0 0" Boundary="55.0404 87.5251 7.8493 3.4049" Font="115" Size="10.56"><ofd:CGTransform CodePosition="0" CodeCount="2" GlyphCount="2"><ofd:Glyphs>55 11</ofd:Glyphs></ofd:CGTransform><ofd:TextCode X="0" Y="8.6275" DeltaX="10.56"></ofd:TextCode></ofd:TextObject><ofd:TextObject ID="203" CTM="0.3528 0 0 0.3528 0 0" Boundary="63.433 87.905 6.1058 2.6636" Font="115" Size="10.56"><ofd:CGTransform CodePosition="0" CodeCount="4" GlyphCount="4"><ofd:Glyphs>33 34 35 1</ofd:Glyphs></ofd:CGTransform><ofd:TextCode X="0" Y="7.5504" DeltaX="5.1638 g 2 5.28">Web </ofd:TextCode></ofd:TextObject><ofd:TextObject ID="204" CTM="0.3528 0 0 0.3528 0 0" Boundary="70.799 87.4692 18.8986 3.5167" Font="115" Size="10.56"><ofd:CGTransform CodePosition="0" CodeCount="5" GlyphCount="5"><ofd:Glyphs>11 12 50 56 57</ofd:Glyphs></ofd:CGTransform><ofd:TextCode X="0" Y="8.7859" DeltaX="10.56 10.4438 10.56 10.4438"></ofd:TextCode></ofd:TextObject><ofd:TextObject ID="205" CTM="0.3528 0 0 0.3528 0 0" Boundary="89.2986 88.0503 95.5853 2.5667" Font="114" Size="10.56"><ofd:CGTransform CodePosition="0" CodeCount="103" GlyphCount="103"><ofd:Glyphs>1 5 5 5 5 5 5 5 5 5 5 5 5 5 5 5 5 5 5 5 5 5 5 5 5 5 5 5 5 5 5 5 5 5 5 5 5 5 5 5 5 5 5 5 5 5 5 5 5 5 5 5 5 5 5 5 5 5 5 5 5 5 5 5 5 5 5 5 5 5 5 5 5 5 5 5 5 5 5 5 5 5 5 5 5 5 5 5 5 5 5 5 5 5 5 5 5 5 5 5 5 1 7</ofd:Glyphs></ofd:CGTransform><ofd:TextCode X="0" Y="7.1386" DeltaX="0.36 g 31 2.64 2.66 g 31 2.64 2.67 g 36 2.64 0.1201"> .................................................................................................... 2</ofd:TextCode></ofd:TextObject><ofd:TextObject ID="212" CTM="0.3528 0 0 0.3528 0 0" Boundary="184.4816 90.5687 0.5588 0" Font="133" Size="10.56"><ofd:CGTransform CodePosition="0" CodeCount="1" GlyphCount="1"><ofd:Glyphs>3</ofd:Glyphs></ofd:CGTransform><ofd:TextCode X="0" Y="0"> </ofd:TextCode></ofd:TextObject><ofd:TextObject ID="213" CTM="0.3528 0 0 0.3528 0 0" Boundary="32.8168 96.4611 2.1905 2.5444" Font="115" Size="10.56"><ofd:CGTransform CodePosition="0" CodeCount="1" GlyphCount="1"><ofd:Glyphs>54</ofd:Glyphs></ofd:CGTransform><ofd:TextCode X="0" Y="7.2969">3</ofd:TextCode></ofd:TextObject><ofd:TextObject ID="214" CTM="0.3528 0 0 0.3528 0 0" Boundary="34.6795 99.0353 0.5588 0" Font="133" Size="10.56"><ofd:CGTransform CodePosition="0" CodeCount="1" GlyphCount="1"><ofd:Glyphs>3</ofd:Glyphs></ofd:CGTransform><ofd:TextCode X="0" Y="0"> </ofd:TextCode></ofd:TextObject><ofd:TextObject ID="215" CTM="0.3528 0 0 0.3528 0 0" Boundary="40.2237 95.9358 22.6389 3.4608" Font="115" Size="10.56"><ofd:CGTransform CodePosition="0" CodeCount="6" GlyphCount="6"><ofd:Glyphs>58 59 60 61 13 62</ofd:Glyphs></ofd:CGTransform><ofd:TextCode X="0" Y="8.7859" DeltaX="g 2 10.56 10.4438 10.56 10.4438"></ofd:TextCode></ofd:TextObject><ofd:TextObject ID="216" CTM="0.3528 0 0 0.3528 0 0" Boundary="62.4487 96.517 122.4352 2.5667" Font="114" Size="10.56"><ofd:CGTransform CodePosition="0" CodeCount="131" GlyphCount="131"><ofd:Glyphs>1 5 5 5 5 5 5 5 5 5 5 5 5 5 5 5 5 5 5 5 5 5 5 5 5 5 5 5 5 5 5 5 5 5 5 5 5 5 5 5 5 5 5 5 5 5 5 5 5 5 5 5 5 5 5 5 5 5 5 5 5 5 5 5 5 5 5 5 5 5 5 5 5 5 5 5 5 5 5 5 5 5 5 5 5 5 5 5 5 5 5 5 5 5 5 5 5 5 5 5 5 5 5 5 5 5 5 5 5 5 5 5 5 5 5 5 5 5 5 5 5 5 5 5 5 5 5 5 5 1 7</ofd:Glyphs></ofd:CGTransform><ofd:TextCode X="0" Y="7.1386" DeltaX="2.55 g 63 2.64 2.66 g 31 2.64 2.67 g 32 2.64 0.1201"> ................................................................................................................................ 2</ofd:TextCode></ofd:TextObject><ofd:TextObject ID="223" CTM="0.3528 0 0 0.3528 0 0" Boundary="184.4816 99.0353 0.5588 0" Font="133" Size="10.56"><ofd:CGTransform CodePosition="0" CodeCount="1" GlyphCount="1"><ofd:Glyphs>3</ofd:Glyphs></ofd:CGTransform><ofd:TextCode X="0" Y="0"> </ofd:TextCode></ofd:TextObject><ofd:TextObject ID="224" CTM="0.3528 0 0 0.3528 0 0" Boundary="40.2237 104.9129 5.7668 2.5742" Font="115" Size="10.56"><ofd:CGTransform CodePosition="0" CodeCount="3" GlyphCount="3"><ofd:Glyphs>54 25 22</ofd:Glyphs></ofd:CGTransform><ofd:TextCode X="0" Y="7.3392" DeltaX="g 2 5.28">3.1</ofd:TextCode></ofd:TextObject><ofd:TextObject ID="225" CTM="0.3528 0 0 0.3528 0 0" Boundary="45.7694 107.502 0.5588 0" Font="133" Size="10.56"><ofd:CGTransform CodePosition="0" CodeCount="1" GlyphCount="1"><ofd:Glyphs>3</ofd:Glyphs></ofd:CGTransform><ofd:TextCode X="0" Y="0"> </ofd:TextCode></ofd:TextObject><ofd:TextObject ID="226" CTM="0.3528 0 0 0.3528 0 0" Boundary="55.0404 104.4025 18.9396 3.4758" Font="115" Size="10.56"><ofd:CGTransform CodePosition="0" CodeCount="5" GlyphCount="5"><ofd:Glyphs>63 64 65 58 66</ofd:Glyphs></ofd:CGTransform><ofd:TextCode X="0" Y="8.7859" DeltaX="g 2 10.56 10.4438 10.56"></ofd:TextCode></ofd:TextObject><ofd:TextObject ID="227" CTM="0.3528 0 0 0.3528 0 0" Boundary="73.593 104.9837 111.291 2.5667" Font="114" Size="10.56"><ofd:CGTransform CodePosition="0" CodeCount="119" GlyphCount="119"><ofd:Glyphs>5 5 5 5 5 5 5 5 5 5 5 5 5 5 5 5 5 5 5 5 5 5 5 5 5 5 5 5 5 5 5 5 5 5 5 5 5 5 5 5 5 5 5 5 5 5 5 5 5 5 5 5 5 5 5 5 5 5 5 5 5 5 5 5 5 5 5 5 5 5 5 5 5 5 5 5 5 5 5 5 5 5 5 5 5 5 5 5 5 5 5 5 5 5 5 5 5 5 5 5 5 5 5 5 5 5 5 5 5 5 5 5 5 5 5 5 5 1 7</ofd:Glyphs></ofd:CGTransform><ofd:TextCode X="0" Y="7.1385" DeltaX="g 63 2.64 2.66 g 31 2.64 2.6701 g 21 2.64 0.12">..................................................................................................................... 2</ofd:TextCode></ofd:TextObject><ofd:TextObject ID="233" CTM="0.3528 0 0 0.3528 0 0" Boundary="184.4816 107.502 0.5588 0" Font="133" Size="10.56"><ofd:CGTransform CodePosition="0" CodeCount="1" GlyphCount="1"><ofd:Glyphs>3</ofd:Glyphs></ofd:CGTransform><ofd:TextCode X="0" Y="0"> </ofd:TextCode></ofd:TextObject><ofd:TextObject ID="234" CTM="0.3528 0 0 0.3528 0 0" Boundary="47.6321 113.3796 9.4921 2.5742" Font="115" Size="10.56"><ofd:CGTransform CodePosition="0" CodeCount="5" GlyphCount="5"><ofd:Glyphs>54 25 22 25 22</ofd:Glyphs></ofd:CGTransform><ofd:TextCode X="0" Y="7.3392" DeltaX="g 4 5.28">3.1.1</ofd:TextCode></ofd:TextObject><ofd:TextObject ID="235" CTM="0.3528 0 0 0.3528 0 0" Boundary="56.9031 115.9687 0.5588 0" Font="133" Size="10.56"><ofd:CGTransform CodePosition="0" CodeCount="1" GlyphCount="1"><ofd:Glyphs>3</ofd:Glyphs></ofd:CGTransform><ofd:TextCode X="0" Y="0"> </ofd:TextCode></ofd:TextObject><ofd:TextObject ID="236" CTM="0.3528 0 0 0.3528 0 0" Boundary="62.4487 112.8953 15.1137 3.4347" Font="115" Size="10.56"><ofd:CGTransform CodePosition="0" CodeCount="4" GlyphCount="4"><ofd:Glyphs>67 59 68 69</ofd:Glyphs></ofd:CGTransform><ofd:TextCode X="0" Y="8.712" DeltaX="g 2 10.56 10.4438"></ofd:TextCode></ofd:TextObject><ofd:TextObject ID="237" CTM="0.3528 0 0 0.3528 0 0" Boundary="77.276 113.4503 107.4552 2.5667" Font="114" Size="10.56"><ofd:CGTransform CodePosition="0" CodeCount="116" GlyphCount="116"><ofd:Glyphs>1 5 5 5 5 5 5 5 5 5 5 5 5 5 5 5 5 5 5 5 5 5 5 5 5 5 5 5 5 5 5 5 5 5 5 5 5 5 5 5 5 5 5 5 5 5 5 5 5 5 5 5 5 5 5 5 5 5 5 5 5 5 5 5 5 5 5 5 5 5 5 5 5 5 5 5 5 5 5 5 5 5 5 5 5 5 5 5 5 5 5 5 5 5 5 5 5 5 5 5 5 5 5 5 5 5 5 5 5 5 5 5 5 5 1 8</ofd:Glyphs></ofd:CGTransform><ofd:TextCode X="0" Y="7.1385" DeltaX="0.12 g 31 2.64 2.66 g 63 2.64 2.67 g 17 2.64 0.1201"> ................................................................................................................. 3</ofd:TextCode></ofd:TextObject><ofd:TextObject ID="244" CTM="0.3528 0 0 0.3528 0 0" Boundary="184.4816 115.9687 0.5588 0" Font="133" Size="10.56"><ofd:CGTransform CodePosition="0" CodeCount="1" GlyphCount="1"><ofd:Glyphs>3</ofd:Glyphs></ofd:CGTransform><ofd:TextCode X="0" Y="0"> </ofd:TextCode></ofd:TextObject><ofd:TextObject ID="245" CTM="0.3528 0 0 0.3528 0 0" Boundary="40.2237 121.8611 5.9158 2.5593" Font="115" Size="10.56"><ofd:CGTransform CodePosition="0" CodeCount="3" GlyphCount="3"><ofd:Glyphs>54 25 28</ofd:Glyphs></ofd:CGTransform><ofd:TextCode X="0" Y="7.297" DeltaX="g 2 5.28">3.2</ofd:TextCode></ofd:TextObject><ofd:TextObject ID="246" CTM="0.3528 0 0 0.3528 0 0" Boundary="45.7694 124.4353 0.5588 0" Font="133" Size="10.56"><ofd:CGTransform CodePosition="0" CodeCount="1" GlyphCount="1"><ofd:Glyphs>3</ofd:Glyphs></ofd:CGTransform><ofd:TextCode X="0" Y="0"> </ofd:TextCode></ofd:TextObject><ofd:TextObject ID="247" CTM="0.3528 0 0 0.3528 0 0" Boundary="55.0404 121.3358 22.4079 3.4608" Font="115" Size="10.56"><ofd:CGTransform CodePosition="0" CodeCount="6" GlyphCount="6"><ofd:Glyphs>58 66 60 61 70 71</ofd:Glyphs></ofd:CGTransform><ofd:TextCode X="0" Y="8.7859" DeltaX="g 2 10.56 10.4438 10.56 10.4438"></ofd:TextCode></ofd:TextObject><ofd:TextObject ID="248" CTM="0.3528 0 0 0.3528 0 0" Boundary="77.276 121.9691 107.5186 2.5146" Font="114" Size="10.56"><ofd:CGTransform CodePosition="0" CodeCount="116" GlyphCount="116"><ofd:Glyphs>1 5 5 5 5 5 5 5 5 5 5 5 5 5 5 5 5 5 5 5 5 5 5 5 5 5 5 5 5 5 5 5 5 5 5 5 5 5 5 5 5 5 5 5 5 5 5 5 5 5 5 5 5 5 5 5 5 5 5 5 5 5 5 5 5 5 5 5 5 5 5 5 5 5 5 5 5 5 5 5 5 5 5 5 5 5 5 5 5 5 5 5 5 5 5 5 5 5 5 5 5 5 5 5 5 5 5 5 5 5 5 5 5 5 1 9</ofd:Glyphs></ofd:CGTransform><ofd:TextCode X="0" Y="6.9907" DeltaX="0.12 g 31 2.64 2.66 g 63 2.64 2.67 g 17 2.64 0.1201"> ................................................................................................................. 5</ofd:TextCode></ofd:TextObject><ofd:TextObject ID="255" CTM="0.3528 0 0 0.3528 0 0" Boundary="184.4816 124.4353 0.5588 0" Font="133" Size="10.56"><ofd:CGTransform CodePosition="0" CodeCount="1" GlyphCount="1"><ofd:Glyphs>3</ofd:Glyphs></ofd:CGTransform><ofd:TextCode X="0" Y="0"> </ofd:TextCode></ofd:TextObject><ofd:TextObject ID="256" CTM="0.3528 0 0 0.3528 0 0" Boundary="47.6321 130.3129 9.4921 2.5742" Font="115" Size="10.56"><ofd:CGTransform CodePosition="0" CodeCount="5" GlyphCount="5"><ofd:Glyphs>54 25 28 25 22</ofd:Glyphs></ofd:CGTransform><ofd:TextCode X="0" Y="7.3392" DeltaX="g 4 5.28">3.2.1</ofd:TextCode></ofd:TextObject><ofd:TextObject ID="257" CTM="0.3528 0 0 0.3528 0 0" Boundary="56.9031 132.902 0.5588 0" Font="133" Size="10.56"><ofd:CGTransform CodePosition="0" CodeCount="1" GlyphCount="1"><ofd:Glyphs>3</ofd:Glyphs></ofd:CGTransform><ofd:TextCode X="0" Y="0"> </ofd:TextCode></ofd:TextObject><ofd:TextObject ID="258" CTM="0.3528 0 0 0.3528 0 0" Boundary="62.4487 129.7876 15.259 3.4757" Font="115" Size="10.56"><ofd:CGTransform CodePosition="0" CodeCount="4" GlyphCount="4"><ofd:Glyphs>72 73 74 75</ofd:Glyphs></ofd:CGTransform><ofd:TextCode X="0" Y="8.8282" DeltaX="g 2 10.56 10.4438"></ofd:TextCode></ofd:TextObject><ofd:TextObject ID="259" CTM="0.3528 0 0 0.3528 0 0" Boundary="77.276 130.4358 107.5186 2.5146" Font="114" Size="10.56"><ofd:CGTransform CodePosition="0" CodeCount="116" GlyphCount="116"><ofd:Glyphs>1 5 5 5 5 5 5 5 5 5 5 5 5 5 5 5 5 5 5 5 5 5 5 5 5 5 5 5 5 5 5 5 5 5 5 5 5 5 5 5 5 5 5 5 5 5 5 5 5 5 5 5 5 5 5 5 5 5 5 5 5 5 5 5 5 5 5 5 5 5 5 5 5 5 5 5 5 5 5 5 5 5 5 5 5 5 5 5 5 5 5 5 5 5 5 5 5 5 5 5 5 5 5 5 5 5 5 5 5 5 5 5 5 5 1 9</ofd:Glyphs></ofd:CGTransform><ofd:TextCode X="0" Y="6.9907" DeltaX="0.12 g 31 2.64 2.66 g 63 2.64 2.67 g 17 2.64 0.1201"> ................................................................................................................. 5</ofd:TextCode></ofd:TextObject><ofd:TextObject ID="266" CTM="0.3528 0 0 0.3528 0 0" Boundary="184.4816 132.902 0.5588 0" Font="133" Size="10.56"><ofd:CGTransform CodePosition="0" CodeCount="1" GlyphCount="1"><ofd:Glyphs>3</ofd:Glyphs></ofd:CGTransform><ofd:TextCode X="0" Y="0"> </ofd:TextCode></ofd:TextObject><ofd:TextObject ID="267" CTM="0.3528 0 0 0.3528 0 0" Boundary="47.6321 138.7944 9.6412 2.5593" Font="115" Size="10.56"><ofd:CGTransform CodePosition="0" CodeCount="5" GlyphCount="5"><ofd:Glyphs>54 25 28 25 28</ofd:Glyphs></ofd:CGTransform><ofd:TextCode X="0" Y="7.297" DeltaX="g 4 5.28">3.2.2</ofd:TextCode></ofd:TextObject><ofd:TextObject ID="268" CTM="0.3528 0 0 0.3528 0 0" Boundary="56.9031 141.3687 0.5588 0" Font="133" Size="10.56"><ofd:CGTransform CodePosition="0" CodeCount="1" GlyphCount="1"><ofd:Glyphs>3</ofd:Glyphs></ofd:CGTransform><ofd:TextCode X="0" Y="0"> </ofd:TextCode></ofd:TextObject><ofd:TextObject ID="269" CTM="0.3528 0 0 0.3528 0 0" Boundary="62.4487 138.2543 15.2441 3.5614" Font="115" Size="10.56"><ofd:CGTransform CodePosition="0" CodeCount="4" GlyphCount="4"><ofd:Glyphs>76 77 78 79</ofd:Glyphs></ofd:CGTransform><ofd:TextCode X="0" Y="8.8282" DeltaX="g 2 10.56 10.4438"></ofd:TextCode></ofd:TextObject><ofd:TextObject ID="270" CTM="0.3528 0 0 0.3528 0 0" Boundary="77.276 138.9025 107.5186 2.5146" Font="114" Size="10.56"><ofd:CGTransform CodePosition="0" CodeCount="116" GlyphCount="116"><ofd:Glyphs>1 5 5 5 5 5 5 5 5 5 5 5 5 5 5 5 5 5 5 5 5 5 5 5 5 5 5 5 5 5 5 5 5 5 5 5 5 5 5 5 5 5 5 5 5 5 5 5 5 5 5 5 5 5 5 5 5 5 5 5 5 5 5 5 5 5 5 5 5 5 5 5 5 5 5 5 5 5 5 5 5 5 5 5 5 5 5 5 5 5 5 5 5 5 5 5 5 5 5 5 5 5 5 5 5 5 5 5 5 5 5 5 5 5 1 9</ofd:Glyphs></ofd:CGTransform><ofd:TextCode X="0" Y="6.9907" DeltaX="0.12 g 31 2.64 2.66 g 63 2.64 2.67 g 17 2.64 0.1201"> ................................................................................................................. 5</ofd:TextCode></ofd:TextObject><ofd:TextObject ID="277" CTM="0.3528 0 0 0.3528 0 0" Boundary="184.4816 141.3687 0.5588 0" Font="133" Size="10.56"><ofd:CGTransform CodePosition="0" CodeCount="1" GlyphCount="1"><ofd:Glyphs>3</ofd:Glyphs></ofd:CGTransform><ofd:TextCode X="0" Y="0"> </ofd:TextCode></ofd:TextObject><ofd:TextObject ID="278" CTM="0.3528 0 0 0.3528 0 0" Boundary="47.6321 147.2682 9.6412 2.5593" Font="115" Size="10.56"><ofd:CGTransform CodePosition="0" CodeCount="5" GlyphCount="5"><ofd:Glyphs>54 25 28 25 54</ofd:Glyphs></ofd:CGTransform><ofd:TextCode X="0" Y="7.297" DeltaX="g 4 5.28">3.2.3</ofd:TextCode></ofd:TextObject><ofd:TextObject ID="279" CTM="0.3528 0 0 0.3528 0 0" Boundary="56.9031 149.8424 0.5588 0" Font="133" Size="10.56"><ofd:CGTransform CodePosition="0" CodeCount="1" GlyphCount="1"><ofd:Glyphs>3</ofd:Glyphs></ofd:CGTransform><ofd:TextCode X="0" Y="0"> </ofd:TextCode></ofd:TextObject><ofd:TextObject ID="280" CTM="0.3528 0 0 0.3528 0 0" Boundary="62.4487 146.7429 22.6687 3.4608" Font="115" Size="10.56"><ofd:CGTransform CodePosition="0" CodeCount="6" GlyphCount="6"><ofd:Glyphs>80 81 10 82 83 84</ofd:Glyphs></ofd:CGTransform><ofd:TextCode X="0" Y="8.7859" DeltaX="g 2 10.56 10.4438 10.56 10.4438">添</ofd:TextCode></ofd:TextObject><ofd:TextObject ID="281" CTM="0.3528 0 0 0.3528 0 0" Boundary="84.6843 147.3762 100.1922 2.5146" Font="114" Size="10.56"><ofd:CGTransform CodePosition="0" CodeCount="108" GlyphCount="108"><ofd:Glyphs>1 5 5 5 5 5 5 5 5 5 5 5 5 5 5 5 5 5 5 5 5 5 5 5 5 5 5 5 5 5 5 5 5 5 5 5 5 5 5 5 5 5 5 5 5 5 5 5 5 5 5 5 5 5 5 5 5 5 5 5 5 5 5 5 5 5 5 5 5 5 5 5 5 5 5 5 5 5 5 5 5 5 5 5 5 5 5 5 5 5 5 5 5 5 5 5 5 5 5 5 5 5 5 5 5 5 1 10</ofd:Glyphs></ofd:CGTransform><ofd:TextCode X="0" Y="6.9907" DeltaX="0.24 g 31 2.64 2.66 g 63 2.64 2.67 g 9 2.64 0.12"> ......................................................................................................... 7</ofd:TextCode></ofd:TextObject><ofd:TextObject ID="288" CTM="0.3528 0 0 0.3528 0 0" Boundary="184.4816 149.8424 0.5588 0" Font="133" Size="10.56"><ofd:CGTransform CodePosition="0" CodeCount="1" GlyphCount="1"><ofd:Glyphs>3</ofd:Glyphs></ofd:CGTransform><ofd:TextCode X="0" Y="0"> </ofd:TextCode></ofd:TextObject><ofd:TextObject ID="289" CTM="0.3528 0 0 0.3528 0 0" Boundary="47.6321 155.7348 9.7417 2.5593" Font="115" Size="10.56"><ofd:CGTransform CodePosition="0" CodeCount="5" GlyphCount="5"><ofd:Glyphs>54 25 28 25 85</ofd:Glyphs></ofd:CGTransform><ofd:TextCode X="0" Y="7.297" DeltaX="g 4 5.28">3.2.4</ofd:TextCode></ofd:TextObject><ofd:TextObject ID="290" CTM="0.3528 0 0 0.3528 0 0" Boundary="56.9031 158.309 0.5588 0" Font="133" Size="10.56"><ofd:CGTransform CodePosition="0" CodeCount="1" GlyphCount="1"><ofd:Glyphs>3</ofd:Glyphs></ofd:CGTransform><ofd:TextCode X="0" Y="0"> </ofd:TextCode></ofd:TextObject><ofd:TextObject ID="291" CTM="0.3528 0 0 0.3528 0 0" Boundary="62.4487 155.2096 22.6836 3.4459" Font="115" Size="10.56"><ofd:CGTransform CodePosition="0" CodeCount="6" GlyphCount="6"><ofd:Glyphs>80 81 86 87 88 89</ofd:Glyphs></ofd:CGTransform><ofd:TextCode X="0" Y="8.7859" DeltaX="g 2 10.56 10.4438 10.56 10.4438">添逻辑</ofd:TextCode></ofd:TextObject><ofd:TextObject ID="292" CTM="0.3528 0 0 0.3528 0 0" Boundary="84.6843 155.7907 100.1996 2.5668" Font="114" Size="10.56"><ofd:CGTransform CodePosition="0" CodeCount="107" GlyphCount="107"><ofd:Glyphs>1 5 5 5 5 5 5 5 5 5 5 5 5 5 5 5 5 5 5 5 5 5 5 5 5 5 5 5 5 5 5 5 5 5 5 5 5 5 5 5 5 5 5 5 5 5 5 5 5 5 5 5 5 5 5 5 5 5 5 5 5 5 5 5 5 5 5 5 5 5 5 5 5 5 5 5 5 5 5 5 5 5 5 5 5 5 5 5 5 5 5 5 5 5 5 5 5 5 5 5 5 5 5 5 1 6 7</ofd:Glyphs></ofd:CGTransform><ofd:TextCode X="0" Y="7.1386" DeltaX="0.24 g 31 2.64 2.66 g 63 2.64 2.67 g 7 2.64 0.1201 5.28"> ....................................................................................................... 12</ofd:TextCode></ofd:TextObject><ofd:TextObject ID="299" CTM="0.3528 0 0 0.3528 0 0" Boundary="184.4816 158.309 0.5588 0" Font="133" Size="10.56"><ofd:CGTransform CodePosition="0" CodeCount="1" GlyphCount="1"><ofd:Glyphs>3</ofd:Glyphs></ofd:CGTransform><ofd:TextCode X="0" Y="0"> </ofd:TextCode></ofd:TextObject><ofd:TextObject ID="300" CTM="0.3528 0 0 0.3528 0 0" Boundary="47.6321 164.2015 9.6412 2.5593" Font="115" Size="10.56"><ofd:CGTransform CodePosition="0" CodeCount="5" GlyphCount="5"><ofd:Glyphs>54 25 28 25 90</ofd:Glyphs></ofd:CGTransform><ofd:TextCode X="0" Y="7.297" DeltaX="g 4 5.28">3.2.5</ofd:TextCode></ofd:TextObject><ofd:TextObject ID="301" CTM="0.3528 0 0 0.3528 0 0" Boundary="56.9031 166.7757 0.5588 0" Font="133" Size="10.56"><ofd:CGTransform CodePosition="0" CodeCount="1" GlyphCount="1"><ofd:Glyphs>3</ofd:Glyphs></ofd:CGTransform><ofd:TextCode X="0" Y="0"> </ofd:TextCode></ofd:TextObject><ofd:TextObject ID="302" CTM="0.3528 0 0 0.3528 0 0" Boundary="62.4487 163.6762 22.5979 3.4757" Font="115" Size="10.56"><ofd:CGTransform CodePosition="0" CodeCount="6" GlyphCount="6"><ofd:Glyphs>80 81 36 82 91 92</ofd:Glyphs></ofd:CGTransform><ofd:TextCode X="0" Y="8.7859" DeltaX="g 2 10.56 10.4438 10.56 10.4438">添</ofd:TextCode></ofd:TextObject><ofd:TextObject ID="303" CTM="0.3528 0 0 0.3528 0 0" Boundary="84.6843 164.2574 100.0469 2.5667" Font="114" Size="10.56"><ofd:CGTransform CodePosition="0" CodeCount="107" GlyphCount="107"><ofd:Glyphs>1 5 5 5 5 5 5 5 5 5 5 5 5 5 5 5 5 5 5 5 5 5 5 5 5 5 5 5 5 5 5 5 5 5 5 5 5 5 5 5 5 5 5 5 5 5 5 5 5 5 5 5 5 5 5 5 5 5 5 5 5 5 5 5 5 5 5 5 5 5 5 5 5 5 5 5 5 5 5 5 5 5 5 5 5 5 5 5 5 5 5 5 5 5 5 5 5 5 5 5 5 5 5 5 1 6 8</ofd:Glyphs></ofd:CGTransform><ofd:TextCode X="0" Y="7.1386" DeltaX="0.24 g 31 2.64 2.66 g 63 2.64 2.67 g 7 2.64 0.1201 5.28"> ....................................................................................................... 13</ofd:TextCode></ofd:TextObject><ofd:TextObject ID="310" CTM="0.3528 0 0 0.3528 0 0" Boundary="184.4816 166.7757 0.5588 0" Font="133" Size="10.56"><ofd:CGTransform CodePosition="0" CodeCount="1" GlyphCount="1"><ofd:Glyphs>3</ofd:Glyphs></ofd:CGTransform><ofd:TextCode X="0" Y="0"> </ofd:TextCode></ofd:TextObject><ofd:TextObject ID="311" CTM="0.3528 0 0 0.3528 0 0" Boundary="40.2237 172.6682 5.9158 2.5593" Font="115" Size="10.56"><ofd:CGTransform CodePosition="0" CodeCount="3" GlyphCount="3"><ofd:Glyphs>54 25 54</ofd:Glyphs></ofd:CGTransform><ofd:TextCode X="0" Y="7.297" DeltaX="g 2 5.28">3.3</ofd:TextCode></ofd:TextObject><ofd:TextObject ID="312" CTM="0.3528 0 0 0.3528 0 0" Boundary="45.7694 175.2424 0.5588 0" Font="133" Size="10.56"><ofd:CGTransform CodePosition="0" CodeCount="1" GlyphCount="1"><ofd:Glyphs>3</ofd:Glyphs></ofd:CGTransform><ofd:TextCode X="0" Y="0"> </ofd:TextCode></ofd:TextObject><ofd:TextObject ID="313" CTM="0.3528 0 0 0.3528 0 0" Boundary="55.0404 172.128 22.6389 3.4906" Font="115" Size="10.56"><ofd:CGTransform CodePosition="0" CodeCount="6" GlyphCount="6"><ofd:Glyphs>67 59 60 12 31 93</ofd:Glyphs></ofd:CGTransform><ofd:TextCode X="0" Y="8.8282" DeltaX="g 2 10.56 10.4438 10.56 10.4438">概</ofd:TextCode></ofd:TextObject><ofd:TextObject ID="314" CTM="0.3528 0 0 0.3528 0 0" Boundary="77.276 172.724 107.5186 2.5668" Font="114" Size="10.56"><ofd:CGTransform CodePosition="0" CodeCount="115" GlyphCount="115"><ofd:Glyphs>1 5 5 5 5 5 5 5 5 5 5 5 5 5 5 5 5 5 5 5 5 5 5 5 5 5 5 5 5 5 5 5 5 5 5 5 5 5 5 5 5 5 5 5 5 5 5 5 5 5 5 5 5 5 5 5 5 5 5 5 5 5 5 5 5 5 5 5 5 5 5 5 5 5 5 5 5 5 5 5 5 5 5 5 5 5 5 5 5 5 5 5 5 5 5 5 5 5 5 5 5 5 5 5 5 5 5 5 5 5 5 5 1 6 9</ofd:Glyphs></ofd:CGTransform><ofd:TextCode X="0" Y="7.1386" DeltaX="0.12 g 31 2.64 2.66 g 63 2.64 2.67 g 15 2.64 0.12 5.28"> ............................................................................................................... 15</ofd:TextCode></ofd:TextObject><ofd:TextObject ID="321" CTM="0.3528 0 0 0.3528 0 0" Boundary="184.4816 175.2424 0.5588 0" Font="133" Size="10.56"><ofd:CGTransform CodePosition="0" CodeCount="1" GlyphCount="1"><ofd:Glyphs>3</ofd:Glyphs></ofd:CGTransform><ofd:TextCode X="0" Y="0"> </ofd:TextCode></ofd:TextObject><ofd:TextObject ID="322" CTM="0.3528 0 0 0.3528 0 0" Boundary="47.6321 181.1199 9.4921 2.5742" Font="115" Size="10.56"><ofd:CGTransform CodePosition="0" CodeCount="5" GlyphCount="5"><ofd:Glyphs>54 25 54 25 22</ofd:Glyphs></ofd:CGTransform><ofd:TextCode X="0" Y="7.3392" DeltaX="g 4 5.28">3.3.1</ofd:TextCode></ofd:TextObject><ofd:TextObject ID="323" CTM="0.3528 0 0 0.3528 0 0" Boundary="56.9031 183.709 0.5588 0" Font="133" Size="10.56"><ofd:CGTransform CodePosition="0" CodeCount="1" GlyphCount="1"><ofd:Glyphs>3</ofd:Glyphs></ofd:CGTransform><ofd:TextCode X="0" Y="0"> </ofd:TextCode></ofd:TextObject><ofd:TextObject ID="324" CTM="0.3528 0 0 0.3528 0 0" Boundary="62.4487 180.6096 18.9843 3.4757" Font="115" Size="10.56"><ofd:CGTransform CodePosition="0" CodeCount="5" GlyphCount="5"><ofd:Glyphs>67 59 94 29 95</ofd:Glyphs></ofd:CGTransform><ofd:TextCode X="0" Y="8.7859" DeltaX="g 2 10.56 10.4438 10.56"></ofd:TextCode></ofd:TextObject><ofd:TextObject ID="325" CTM="0.3528 0 0 0.3528 0 0" Boundary="81.0013 181.1907 103.7932 2.5668" Font="114" Size="10.56"><ofd:CGTransform CodePosition="0" CodeCount="111" GlyphCount="111"><ofd:Glyphs>1 5 5 5 5 5 5 5 5 5 5 5 5 5 5 5 5 5 5 5 5 5 5 5 5 5 5 5 5 5 5 5 5 5 5 5 5 5 5 5 5 5 5 5 5 5 5 5 5 5 5 5 5 5 5 5 5 5 5 5 5 5 5 5 5 5 5 5 5 5 5 5 5 5 5 5 5 5 5 5 5 5 5 5 5 5 5 5 5 5 5 5 5 5 5 5 5 5 5 5 5 5 5 5 5 5 5 5 1 6 9</ofd:Glyphs></ofd:CGTransform><ofd:TextCode X="0" Y="7.1386" DeltaX="0.12 g 31 2.64 2.66 g 63 2.64 2.67 g 11 2.64 0.12 5.28"> ........................................................................................................... 15</ofd:TextCode></ofd:TextObject><ofd:TextObject ID="332" CTM="0.3528 0 0 0.3528 0 0" Boundary="184.4816 183.709 0.5588 0" Font="133" Size="10.56"><ofd:CGTransform CodePosition="0" CodeCount="1" GlyphCount="1"><ofd:Glyphs>3</ofd:Glyphs></ofd:CGTransform><ofd:TextCode X="0" Y="0"> </ofd:TextCode></ofd:TextObject><ofd:TextObject ID="333" CTM="0.3528 0 0 0.3528 0 0" Boundary="47.6321 189.6015 9.6412 2.5593" Font="115" Size="10.56"><ofd:CGTransform CodePosition="0" CodeCount="5" GlyphCount="5"><ofd:Glyphs>54 25 54 25 28</ofd:Glyphs></ofd:CGTransform><ofd:TextCode X="0" Y="7.297" DeltaX="g 4 5.28">3.3.2</ofd:TextCode></ofd:TextObject><ofd:TextObject ID="334" CTM="0.3528 0 0 0.3528 0 0" Boundary="56.9031 192.1757 0.5588 0" Font="133" Size="10.56"><ofd:CGTransform CodePosition="0" CodeCount="1" GlyphCount="1"><ofd:Glyphs>3</ofd:Glyphs></ofd:CGTransform><ofd:TextCode X="0" Y="0"> </ofd:TextCode></ofd:TextObject><ofd:TextObject ID="335" CTM="0.3528 0 0 0.3528 0 0" Boundary="62.4487 189.0762 26.3083 3.4608" Font="115" Size="10.56"><ofd:CGTransform CodePosition="0" CodeCount="7" GlyphCount="7"><ofd:Glyphs>58 59 94 96 97 98 99</ofd:Glyphs></ofd:CGTransform><ofd:TextCode X="0" Y="8.7859" DeltaX="g 2 10.56 10.4438 10.56 10.4438 10.56"></ofd:TextCode></ofd:TextObject><ofd:TextObject ID="336" CTM="0.3528 0 0 0.3528 0 0" Boundary="88.4096 189.6574 96.4855 2.5668" Font="114" Size="10.56"><ofd:CGTransform CodePosition="0" CodeCount="103" GlyphCount="103"><ofd:Glyphs>1 5 5 5 5 5 5 5 5 5 5 5 5 5 5 5 5 5 5 5 5 5 5 5 5 5 5 5 5 5 5 5 5 5 5 5 5 5 5 5 5 5 5 5 5 5 5 5 5 5 5 5 5 5 5 5 5 5 5 5 5 5 5 5 5 5 5 5 5 5 5 5 5 5 5 5 5 5 5 5 5 5 5 5 5 5 5 5 5 5 5 5 5 5 5 5 5 5 5 5 1 6 11</ofd:Glyphs></ofd:CGTransform><ofd:TextCode X="0" Y="7.1385" DeltaX="0.24 g 31 2.64 2.66 g 31 2.64 2.6701 g 35 2.64 0.1201 5.28"> ................................................................................................... 16</ofd:TextCode></ofd:TextObject><ofd:TextObject ID="343" CTM="0.3528 0 0 0.3528 0 0" Boundary="184.4816 192.1757 0.5588 0" Font="133" Size="10.56"><ofd:CGTransform CodePosition="0" CodeCount="1" GlyphCount="1"><ofd:Glyphs>3</ofd:Glyphs></ofd:CGTransform><ofd:TextCode X="0" Y="0"> </ofd:TextCode></ofd:TextObject><ofd:TextObject ID="344" CTM="0.3528 0 0 0.3528 0 0" Boundary="47.6321 198.0682 9.6412 2.5593" Font="115" Size="10.56"><ofd:CGTransform CodePosition="0" CodeCount="5" GlyphCount="5"><ofd:Glyphs>54 25 54 25 54</ofd:Glyphs></ofd:CGTransform><ofd:TextCode X="0" Y="7.297" DeltaX="g 4 5.28">3.3.3</ofd:TextCode></ofd:TextObject><ofd:TextObject ID="345" CTM="0.3528 0 0 0.3528 0 0" Boundary="56.9031 200.6424 0.5588 0" Font="133" Size="10.56"><ofd:CGTransform CodePosition="0" CodeCount="1" GlyphCount="1"><ofd:Glyphs>3</ofd:Glyphs></ofd:CGTransform><ofd:TextCode X="0" Y="0"> </ofd:TextCode></ofd:TextObject><ofd:TextObject ID="346" CTM="0.3528 0 0 0.3528 0 0" Boundary="62.4487 197.528 18.8129 3.4906" Font="115" Size="10.56"><ofd:CGTransform CodePosition="0" CodeCount="5" GlyphCount="5"><ofd:Glyphs>67 66 100 101 45</ofd:Glyphs></ofd:CGTransform><ofd:TextCode X="0" Y="8.8282" DeltaX="g 2 10.56 g 2 10.4438"></ofd:TextCode></ofd:TextObject><ofd:TextObject ID="347" CTM="0.3528 0 0 0.3528 0 0" Boundary="81.9326 198.0384 5.7966 2.5444" Font="115" Size="10.56"><ofd:CGTransform CodePosition="0" CodeCount="3" GlyphCount="3"><ofd:Glyphs>102 103 104</ofd:Glyphs></ofd:CGTransform><ofd:TextCode X="0" Y="7.3814" DeltaX="g 2 5.28">API</ofd:TextCode></ofd:TextObject><ofd:TextObject ID="348" CTM="0.3528 0 0 0.3528 0 0" Boundary="87.4783 198.124 97.346 2.5668" Font="114" Size="10.56"><ofd:CGTransform CodePosition="0" CodeCount="104" GlyphCount="104"><ofd:Glyphs>1 5 5 5 5 5 5 5 5 5 5 5 5 5 5 5 5 5 5 5 5 5 5 5 5 5 5 5 5 5 5 5 5 5 5 5 5 5 5 5 5 5 5 5 5 5 5 5 5 5 5 5 5 5 5 5 5 5 5 5 5 5 5 5 5 5 5 5 5 5 5 5 5 5 5 5 5 5 5 5 5 5 5 5 5 5 5 5 5 5 5 5 5 5 5 5 5 5 5 5 5 1 6 12</ofd:Glyphs></ofd:CGTransform><ofd:TextCode X="0" Y="7.1386" DeltaX="0.24 g 31 2.64 2.66 g 31 2.64 2.67 g 31 2.64 2.6401 g 4 2.64 0.12 5.28"> .................................................................................................... 18</ofd:TextCode></ofd:TextObject><ofd:TextObject ID="355" CTM="0.3528 0 0 0.3528 0 0" Boundary="184.4816 200.6424 0.5588 0" Font="133" Size="10.56"><ofd:CGTransform CodePosition="0" CodeCount="1" GlyphCount="1"><ofd:Glyphs>3</ofd:Glyphs></ofd:CGTransform><ofd:TextCode X="0" Y="0"> </ofd:TextCode></ofd:TextObject><ofd:TextObject ID="356" CTM="0.3528 0 0 0.3528 0 0" Boundary="47.6321 206.5454 9.7417 2.5593" Font="115" Size="10.56"><ofd:CGTransform CodePosition="0" CodeCount="5" GlyphCount="5"><ofd:Glyphs>54 25 54 25 85</ofd:Glyphs></ofd:CGTransform><ofd:TextCode X="0" Y="7.297" DeltaX="g 4 5.28">3.3.4</ofd:TextCode></ofd:TextObject><ofd:TextObject ID="357" CTM="0.3528 0 0 0.3528 0 0" Boundary="56.9031 209.1196 0.5588 0" Font="133" Size="10.56"><ofd:CGTransform CodePosition="0" CodeCount="1" GlyphCount="1"><ofd:Glyphs>3</ofd:Glyphs></ofd:CGTransform><ofd:TextCode X="0" Y="0"> </ofd:TextCode></ofd:TextObject><ofd:TextObject ID="358" CTM="0.3528 0 0 0.3528 0 0" Boundary="62.4487 206.035 18.8837 3.4608" Font="115" Size="10.56"><ofd:CGTransform CodePosition="0" CodeCount="5" GlyphCount="5"><ofd:Glyphs>105 106 107 108 3</ofd:Glyphs></ofd:CGTransform><ofd:TextCode X="0" Y="8.7437" DeltaX="g 2 10.56 10.4438 10.56"></ofd:TextCode></ofd:TextObject><ofd:TextObject ID="359" CTM="0.3528 0 0 0.3528 0 0" Boundary="81.0013 206.6013 103.905 2.5668" Font="114" Size="10.56"><ofd:CGTransform CodePosition="0" CodeCount="111" GlyphCount="111"><ofd:Glyphs>1 5 5 5 5 5 5 5 5 5 5 5 5 5 5 5 5 5 5 5 5 5 5 5 5 5 5 5 5 5 5 5 5 5 5 5 5 5 5 5 5 5 5 5 5 5 5 5 5 5 5 5 5 5 5 5 5 5 5 5 5 5 5 5 5 5 5 5 5 5 5 5 5 5 5 5 5 5 5 5 5 5 5 5 5 5 5 5 5 5 5 5 5 5 5 5 5 5 5 5 5 5 5 5 5 5 5 5 1 7 13</ofd:Glyphs></ofd:CGTransform><ofd:TextCode X="0" Y="7.1386" DeltaX="0.12 g 31 2.64 2.66 g 63 2.64 2.67 g 11 2.64 0.12 5.28"> ........................................................................................................... 20</ofd:TextCode></ofd:TextObject><ofd:TextObject ID="366" CTM="0.3528 0 0 0.3528 0 0" Boundary="184.4816 209.1196 0.5588 0" Font="133" Size="10.56"><ofd:CGTransform CodePosition="0" CodeCount="1" GlyphCount="1"><ofd:Glyphs>3</ofd:Glyphs></ofd:CGTransform><ofd:TextCode X="0" Y="0"> </ofd:TextCode></ofd:TextObject><ofd:TextObject ID="367" CTM="0.3528 0 0 0.3528 0 0" Boundary="47.6321 215.0121 9.6412 2.5593" Font="115" Size="10.56"><ofd:CGTransform CodePosition="0" CodeCount="5" GlyphCount="5"><ofd:Glyphs>54 25 54 25 90</ofd:Glyphs></ofd:CGTransform><ofd:TextCode X="0" Y="7.297" DeltaX="g 4 5.28">3.3.5</ofd:TextCode></ofd:TextObject><ofd:TextObject ID="368" CTM="0.3528 0 0 0.3528 0 0" Boundary="56.9031 217.5863 0.5588 0" Font="133" Size="10.56"><ofd:CGTransform CodePosition="0" CodeCount="1" GlyphCount="1"><ofd:Glyphs>3</ofd:Glyphs></ofd:CGTransform><ofd:TextCode X="0" Y="0"> </ofd:TextCode></ofd:TextObject><ofd:TextObject ID="369" CTM="0.3528 0 0 0.3528 0 0" Boundary="62.4487 214.4719 33.8335 3.5018" Font="115" Size="10.56"><ofd:CGTransform CodePosition="0" CodeCount="9" GlyphCount="9"><ofd:Glyphs>109 110 111 112 113 114 115 116 117</ofd:Glyphs></ofd:CGTransform><ofd:TextCode X="0" Y="8.8282" DeltaX="g 2 10.56 10.4438 10.56 10.4438 10.56 10.4438 10.56">隐</ofd:TextCode></ofd:TextObject><ofd:TextObject ID="370" CTM="0.3528 0 0 0.3528 0 0" Boundary="95.818 215.068 89.0883 2.5668" Font="114" Size="10.56"><ofd:CGTransform CodePosition="0" CodeCount="95" GlyphCount="95"><ofd:Glyphs>1 5 5 5 5 5 5 5 5 5 5 5 5 5 5 5 5 5 5 5 5 5 5 5 5 5 5 5 5 5 5 5 5 5 5 5 5 5 5 5 5 5 5 5 5 5 5 5 5 5 5 5 5 5 5 5 5 5 5 5 5 5 5 5 5 5 5 5 5 5 5 5 5 5 5 5 5 5 5 5 5 5 5 5 5 5 5 5 5 5 5 5 1 7 13</ofd:Glyphs></ofd:CGTransform><ofd:TextCode X="0" Y="7.1386" DeltaX="0.36 g 31 2.64 2.66 g 31 2.64 2.67 g 27 2.64 0.1201 5.28"> ........................................................................................... 20</ofd:TextCode></ofd:TextObject><ofd:TextObject ID="376" CTM="0.3528 0 0 0.3528 0 0" Boundary="184.4816 217.5863 0.5588 0" Font="133" Size="10.56"><ofd:CGTransform CodePosition="0" CodeCount="1" GlyphCount="1"><ofd:Glyphs>3</ofd:Glyphs></ofd:CGTransform><ofd:TextCode X="0" Y="0"> </ofd:TextCode></ofd:TextObject><ofd:TextObject ID="377" CTM="0.3528 0 0 0.3528 0 0" Boundary="40.2237 223.4788 6.0164 2.5593" Font="115" Size="10.56"><ofd:CGTransform CodePosition="0" CodeCount="3" GlyphCount="3"><ofd:Glyphs>54 25 85</ofd:Glyphs></ofd:CGTransform><ofd:TextCode X="0" Y="7.297" DeltaX="g 2 5.28">3.4</ofd:TextCode></ofd:TextObject><ofd:TextObject ID="378" CTM="0.3528 0 0 0.3528 0 0" Boundary="45.7694 226.053 0.5588 0" Font="133" Size="10.56"><ofd:CGTransform CodePosition="0" CodeCount="1" GlyphCount="1"><ofd:Glyphs>3</ofd:Glyphs></ofd:CGTransform><ofd:TextCode X="0" Y="0"> </ofd:TextCode></ofd:TextObject><ofd:TextObject ID="379" CTM="0.3528 0 0 0.3528 0 0" Boundary="55.0404 222.9386 22.6985 3.5018" Font="115" Size="10.56"><ofd:CGTransform CodePosition="0" CodeCount="6" GlyphCount="6"><ofd:Glyphs>118 75 29 119 120 121</ofd:Glyphs></ofd:CGTransform><ofd:TextCode X="0" Y="8.8282" DeltaX="g 2 10.56 10.4438 10.56 10.4438"></ofd:TextCode></ofd:TextObject><ofd:TextObject ID="380" CTM="0.3528 0 0 0.3528 0 0" Boundary="77.276 223.5346 107.6303 2.5668" Font="114" Size="10.56"><ofd:CGTransform CodePosition="0" CodeCount="115" GlyphCount="115"><ofd:Glyphs>1 5 5 5 5 5 5 5 5 5 5 5 5 5 5 5 5 5 5 5 5 5 5 5 5 5 5 5 5 5 5 5 5 5 5 5 5 5 5 5 5 5 5 5 5 5 5 5 5 5 5 5 5 5 5 5 5 5 5 5 5 5 5 5 5 5 5 5 5 5 5 5 5 5 5 5 5 5 5 5 5 5 5 5 5 5 5 5 5 5 5 5 5 5 5 5 5 5 5 5 5 5 5 5 5 5 5 5 5 5 5 5 1 7 13</ofd:Glyphs></ofd:CGTransform><ofd:TextCode X="0" Y="7.1386" DeltaX="0.12 g 31 2.64 2.66 g 63 2.64 2.67 g 15 2.64 0.12 5.28"> ............................................................................................................... 20</ofd:TextCode></ofd:TextObject><ofd:TextObject ID="387" CTM="0.3528 0 0 0.3528 0 0" Boundary="184.4816 226.053 0.5588 0" Font="133" Size="10.56"><ofd:CGTransform CodePosition="0" CodeCount="1" GlyphCount="1"><ofd:Glyphs>3</ofd:Glyphs></ofd:CGTransform><ofd:TextCode X="0" Y="0"> </ofd:TextCode></ofd:TextObject><ofd:TextObject ID="388" CTM="0.3528 0 0 0.3528 0 0" Boundary="47.6321 231.9305 9.4921 2.5742" Font="115" Size="10.56"><ofd:CGTransform CodePosition="0" CodeCount="5" GlyphCount="5"><ofd:Glyphs>54 25 85 25 22</ofd:Glyphs></ofd:CGTransform><ofd:TextCode X="0" Y="7.3392" DeltaX="g 4 5.28">3.4.1</ofd:TextCode></ofd:TextObject><ofd:TextObject ID="389" CTM="0.3528 0 0 0.3528 0 0" Boundary="56.9031 234.5196 0.5588 0" Font="133" Size="10.56"><ofd:CGTransform CodePosition="0" CodeCount="1" GlyphCount="1"><ofd:Glyphs>3</ofd:Glyphs></ofd:CGTransform><ofd:TextCode X="0" Y="0"> </ofd:TextCode></ofd:TextObject><ofd:TextObject ID="390" CTM="0.3528 0 0 0.3528 0 0" Boundary="62.4487 231.4053 15.2292 3.4906" Font="115" Size="10.56"><ofd:CGTransform CodePosition="0" CodeCount="4" GlyphCount="4"><ofd:Glyphs>122 123 31 93</ofd:Glyphs></ofd:CGTransform><ofd:TextCode X="0" Y="8.8282" DeltaX="g 2 10.56 10.4438">概</ofd:TextCode></ofd:TextObject><ofd:TextObject ID="391" CTM="0.3528 0 0 0.3528 0 0" Boundary="77.276 232.0013 107.6303 2.5668" Font="114" Size="10.56"><ofd:CGTransform CodePosition="0" CodeCount="115" GlyphCount="115"><ofd:Glyphs>1 5 5 5 5 5 5 5 5 5 5 5 5 5 5 5 5 5 5 5 5 5 5 5 5 5 5 5 5 5 5 5 5 5 5 5 5 5 5 5 5 5 5 5 5 5 5 5 5 5 5 5 5 5 5 5 5 5 5 5 5 5 5 5 5 5 5 5 5 5 5 5 5 5 5 5 5 5 5 5 5 5 5 5 5 5 5 5 5 5 5 5 5 5 5 5 5 5 5 5 5 5 5 5 5 5 5 5 5 5 5 5 1 7 13</ofd:Glyphs></ofd:CGTransform><ofd:TextCode X="0" Y="7.1386" DeltaX="0.12 g 31 2.64 2.66 g 63 2.64 2.67 g 15 2.64 0.12 5.28"> ............................................................................................................... 20</ofd:TextCode></ofd:TextObject><ofd:TextObject ID="398" CTM="0.3528 0 0 0.3528 0 0" Boundary="184.4816 234.5196 0.5588 0" Font="133" Size="10.56"><ofd:CGTransform CodePosition="0" CodeCount="1" GlyphCount="1"><ofd:Glyphs>3</ofd:Glyphs></ofd:CGTransform><ofd:TextCode X="0" Y="0"> </ofd:TextCode></ofd:TextObject><ofd:TextObject ID="399" CTM="0.3528 0 0 0.3528 0 0" Boundary="40.2237 240.4121 5.9158 2.5593" Font="115" Size="10.56"><ofd:CGTransform CodePosition="0" CodeCount="3" GlyphCount="3"><ofd:Glyphs>54 25 90</ofd:Glyphs></ofd:CGTransform><ofd:TextCode X="0" Y="7.297" DeltaX="g 2 5.28">3.5</ofd:TextCode></ofd:TextObject><ofd:TextObject ID="400" CTM="0.3528 0 0 0.3528 0 0" Boundary="45.7694 242.9863 0.5588 0" Font="133" Size="10.56"><ofd:CGTransform CodePosition="0" CodeCount="1" GlyphCount="1"><ofd:Glyphs>3</ofd:Glyphs></ofd:CGTransform><ofd:TextCode X="0" Y="0"> </ofd:TextCode></ofd:TextObject><ofd:TextObject ID="401" CTM="0.3528 0 0 0.3528 0 0" Boundary="55.0404 239.8868 22.6538 3.4869" Font="115" Size="10.56"><ofd:CGTransform CodePosition="0" CodeCount="6" GlyphCount="6"><ofd:Glyphs>124 36 125 126 127 41</ofd:Glyphs></ofd:CGTransform><ofd:TextCode X="0" Y="8.7859" DeltaX="g 2 10.56 10.4438 10.56 10.4438">脚</ofd:TextCode></ofd:TextObject><ofd:TextObject ID="402" CTM="0.3528 0 0 0.3528 0 0" Boundary="77.276 240.468 107.6341 2.5668" Font="114" Size="10.56"><ofd:CGTransform CodePosition="0" CodeCount="115" GlyphCount="115"><ofd:Glyphs>1 5 5 5 5 5 5 5 5 5 5 5 5 5 5 5 5 5 5 5 5 5 5 5 5 5 5 5 5 5 5 5 5 5 5 5 5 5 5 5 5 5 5 5 5 5 5 5 5 5 5 5 5 5 5 5 5 5 5 5 5 5 5 5 5 5 5 5 5 5 5 5 5 5 5 5 5 5 5 5 5 5 5 5 5 5 5 5 5 5 5 5 5 5 5 5 5 5 5 5 5 5 5 5 5 5 5 5 5 5 5 5 1 7 14</ofd:Glyphs></ofd:CGTransform><ofd:TextCode X="0" Y="7.1385" DeltaX="0.12 g 31 2.64 2.66 g 63 2.64 2.67 g 15 2.64 0.12 5.28"> ............................................................................................................... 24</ofd:TextCode></ofd:TextObject><ofd:TextObject ID="409" CTM="0.3528 0 0 0.3528 0 0" Boundary="184.4816 242.9863 0.5588 0" Font="133" Size="10.56"><ofd:CGTransform CodePosition="0" CodeCount="1" GlyphCount="1"><ofd:Glyphs>3</ofd:Glyphs></ofd:CGTransform><ofd:TextCode X="0" Y="0"> </ofd:TextCode></ofd:TextObject><ofd:TextObject ID="410" CTM="0.3528 0 0 0.3528 0 0" Boundary="47.6321 248.8639 9.4921 2.5742" Font="115" Size="10.56"><ofd:CGTransform CodePosition="0" CodeCount="5" GlyphCount="5"><ofd:Glyphs>54 25 90 25 22</ofd:Glyphs></ofd:CGTransform><ofd:TextCode X="0" Y="7.3392" DeltaX="g 4 5.28">3.5.1</ofd:TextCode></ofd:TextObject><ofd:TextObject ID="411" CTM="0.3528 0 0 0.3528 0 0" Boundary="56.9031 251.453 0.5588 0" Font="133" Size="10.56"><ofd:CGTransform CodePosition="0" CodeCount="1" GlyphCount="1"><ofd:Glyphs>3</ofd:Glyphs></ofd:CGTransform><ofd:TextCode X="0" Y="0"> </ofd:TextCode></ofd:TextObject><ofd:TextObject ID="412" CTM="0.3528 0 0 0.3528 0 0" Boundary="62.4487 248.3535 22.6538 3.4869" Font="115" Size="10.56"><ofd:CGTransform CodePosition="0" CodeCount="6" GlyphCount="6"><ofd:Glyphs>128 18 125 126 127 41</ofd:Glyphs></ofd:CGTransform><ofd:TextCode X="0" Y="8.7859" DeltaX="g 2 10.56 10.4438 10.56 10.4438">册脚</ofd:TextCode></ofd:TextObject><ofd:TextObject ID="413" CTM="0.3528 0 0 0.3528 0 0" Boundary="84.6843 248.9346 100.2257 2.5668" Font="114" Size="10.56"><ofd:CGTransform CodePosition="0" CodeCount="107" GlyphCount="107"><ofd:Glyphs>1 5 5 5 5 5 5 5 5 5 5 5 5 5 5 5 5 5 5 5 5 5 5 5 5 5 5 5 5 5 5 5 5 5 5 5 5 5 5 5 5 5 5 5 5 5 5 5 5 5 5 5 5 5 5 5 5 5 5 5 5 5 5 5 5 5 5 5 5 5 5 5 5 5 5 5 5 5 5 5 5 5 5 5 5 5 5 5 5 5 5 5 5 5 5 5 5 5 5 5 5 5 5 5 1 7 14</ofd:Glyphs></ofd:CGTransform><ofd:TextCode X="0" Y="7.1386" DeltaX="0.24 g 31 2.64 2.66 g 63 2.64 2.67 g 7 2.64 0.1201 5.28"> ....................................................................................................... 24</ofd:TextCode></ofd:TextObject><ofd:TextObject ID="420" CTM="0.3528 0 0 0.3528 0 0" Boundary="184.4816 251.453 0.5588 0" Font="133" Size="10.56"><ofd:CGTransform CodePosition="0" CodeCount="1" GlyphCount="1"><ofd:Glyphs>3</ofd:Glyphs></ofd:CGTransform><ofd:TextCode X="0" Y="0"> </ofd:TextCode></ofd:TextObject></ofd:Layer></ofd:Content></ofd:Page>
